README.md
setup.cfg
setup.py
blkchn/__init__.py
blkchn/blockchain.py
blkchn.egg-info/PKG-INFO
blkchn.egg-info/SOURCES.txt
blkchn.egg-info/dependency_links.txt
blkchn.egg-info/requires.txt
blkchn.egg-info/top_level.txt
test/test_blockchain.py