Metadata-Version: 1.1
Name: blkchn
Version: 0.0.6
Summary: Blockchain data structure
Home-page: https://github.com/tomcusack1/blkchn
Author: Tom Cusack-Huang
Author-email: tom@cusack-huang.com
License: MIT
Download-URL: https://github.com/tomcusack1/blkchn/archive/v0.0.4.tar.gz
Platform: UNKNOWN
